{"itemid":1835946060,"shortname":"electric.cabletunnel","Name":"Cable Tunnel","Description":"Allows you to pass a cable through a wall. Each input will forward the amount it receives to the corresponding output on the other side.","Category":"Electrical","maxDraggable":0,"ItemType":"Generic","AmountType":"Count","stackable":1,"quickDespawn":false,"rarity":"None","condition":{"enabled":false,"max":100.0,"repairable":false},"Parent":0,"isWearable":false,"isHoldable":true,"isUsable":true,"HasSkins":false}